Workbook

Sheet Resumen (texto completo)
A1: Evaluación a texto completo — Revisión sistemática (TDDMachine)
A2: Criterio de inclusión: estudios primarios (artículos de revista, ponencias de congreso, capítulos de libro, libros) con calidad metodológica suficiente y pertinentes al objetivo. Criterios de exclusión aplicados abajo.
A4: A. Estudios evaluados a texto completo, por categoría
A5: Categoría | B5: Evaluados | C5: Incluidos | D5: Excluidos
A6: Requisitos funcionales | B6: =COUNTIF('Estudios incluidos'!$B:$B,"Requisitos funcionales")+COUNTIF('Estudios excluidos'!$B:$B,"Requisitos funcionales") -> 121 | C6: =COUNTIF('Estudios incluidos'!$B:$B,"Requisitos funcionales") -> 86 | D6: =COUNTIF('Estudios excluidos'!$B:$B,"Requisitos funcionales") -> 35
A7: Casos de uso | B7: =COUNTIF('Estudios incluidos'!$B:$B,"Casos de uso")+COUNTIF('Estudios excluidos'!$B:$B,"Casos de uso") -> 22 | C7: =COUNTIF('Estudios incluidos'!$B:$B,"Casos de uso") -> 13 | D7: =COUNTIF('Estudios excluidos'!$B:$B,"Casos de uso") -> 9
A8: Historias de usuario | B8: =COUNTIF('Estudios incluidos'!$B:$B,"Historias de usuario")+COUNTIF('Estudios excluidos'!$B:$B,"Historias de usuario") -> 11 | C8: =COUNTIF('Estudios incluidos'!$B:$B,"Historias de usuario") -> 9 | D8: =COUNTIF('Estudios excluidos'!$B:$B,"Historias de usuario") -> 2
A9: Total | B9: =SUM(B6:B8) -> 154 | C9: =SUM(C6:C8) -> 108 | D9: =SUM(D6:D8) -> 46
A11: B. Estudios incluidos por tipo de publicación (criterio de inclusión)
A12: Tipo de estudio primario | B12: Incluidos
A13: Artículo de revista | B13: =COUNTIF('Estudios incluidos'!$C:$C,"Articulo de revista") -> 35
A14: Ponencia de congreso | B14: =COUNTIF('Estudios incluidos'!$C:$C,"Ponencia de congreso") -> 72
A15: Capítulo de libro | B15: =COUNTIF('Estudios incluidos'!$C:$C,"Capitulo de libro") -> 0
A16: Libro | B16: =COUNTIF('Estudios incluidos'!$C:$C,"Libro") -> 0
A17: Tesis doctoral | B17: =COUNTIF('Estudios incluidos'!$C:$C,"Tesis doctoral") -> 1
A18: Total incluidos | B18: =SUM(B13:B17) -> 108
A20: C. Estudios excluidos por criterio (en lectura a texto completo)
A21: Motivo de exclusión | B21: Excluidos
A22: Fuera de alcance temático | B22: =COUNTIF('Estudios excluidos'!$I:$I,"Fuera de alcance temático") -> 27
A23: Calidad insuficiente | B23: =COUNTIF('Estudios excluidos'!$I:$I,"Calidad insuficiente") -> 16
A24: Estudio secundario | B24: =COUNTIF('Estudios excluidos'!$I:$I,"Estudio secundario") -> 3
A25: Total excluidos | B25: =SUM(B22:B24) -> 46
A27: Nota: exclusiones previas a la lectura a texto completo (reportadas en el flujo PRISMA, hoja 'Flujo PRISMA'): estudios secundarios 12, no-artículos/actas de congreso 8, sin acceso a texto completo 5, duplicados entre categorías 9. El tipo de estudio se determinó a partir de los metadatos de la fuente (revista, actas de congreso, capítulo de libro).

Sheet Flujo PRISMA
A1: Flujo PRISMA — identificación, cribado y elegibilidad (búsqueda en bases)
A3: Registros identificados (4 bases) | B3: 6795
A4: Tras eliminación de duplicados | B4: 5628
A5: Tras elegibilidad (≥2015, inglés) | B5: 2870
A6: – Excluidos en cribado por título/resumen (no pertinentes al objetivo, no-artículos, estudios secundarios, sin acceso, duplicados entre categorías) | B6: −2716
A7: Seleccionados a texto completo (incluye estudios complementarios de HU y 1 del volumen ICSR 2016) | B7: 154
A8: – Excluidos en lectura a texto completo (fuera de alcance 27, calidad insuficiente 16, secundario 3) | B8: −46
A9: Estudios incluidos | B9: 108

Sheet Estudios incluidos
A1: N° | B1: Categoría | C1: Tipo de estudio | D1: Año | E1: DOI | F1: Título | G1: Enlace | H1: QA1 | I1: QA2 | J1: QA3 | K1: QA4 | L1: Calidad (0-4) | M1: Estándares/metodologías | N1: Campos de especificación | O1: Herramienta CASE | P1: Relación con generación de pruebas | Q1: Aporte principal
A2: 1 | B2: Requisitos funcionales | C2: Ponencia de congreso | D2: 2023 | E2: 10.65109/kgpx8966 | F2: A Behaviour-Driven Approach for Testing Requirements via User and System Stories in Agent Systems | G2: https://doi.org/10.65109/kgpx8966 | H2: 1 | I2: 1 | J2: 0.5 | K2: 1 | L2: 3.5 | M2: Gherkin/BDD, User and System Stories (USS), acceptance criteria Given-When-Then | N2: acceptance criteria (Given/When/Then), goal-context, goal-success, goal-failure, goal-plan, belief-inference, perception | O2: Framework propio integrando Cucumber, JUnit, Mockito y PITest sobre SARL | P2: Las historias de usuario y sistema (USS) extendidas con anotaciones de tipo (goal, plan, belief, perception) se traducen mediante Cucumber en definiciones de pasos que generan tests ejecutables (JUnit/Mockito), evaluados posteriormente con mutation testing (PITest). | Q2: Extiende las User and System Stories con estructura BDD (condiciones de éxito/fallo de metas, planes, inferencia de creencias y percepciones) e implementa un framework de pruebas que integra herramientas industriales estándar para agentes BDI.
A3: 2 | B3: Requisitos funcionales | C3: Ponencia de congreso | D3: 2019 | E3: 10.1145/3350768.3351300 | F3: A Conceptual Metamodel to Bridging Requirement Patterns to Test Patterns | G3: https://doi.org/10.1145/3350768.3351300 | H3: 1 | I3: 1 | J3: 0.5 | K3: 1 | L3: 3.5 | M3: BDD, Gherkin, Page Object Model (POM), MOF (OMG) | N3: Feature (user story As/I can/So that), Scenario, Example, Steps (Given/When/Then), UIElement, business rules, atributos de patrón (Name, Author, Version, Goal, Source, Context, Keywords) | O3: SoPaMM (Software Pattern MetaModel); prueba de concepto con Maven, JUnit y Selenium WebDriver | P3: Los requirement patterns se modelan con conceptos BDD (Feature/Scenario/Example) que son reutilizados directamente por los test patterns (TestCase + Steps + UIElement), permitiendo generar y automatizar casos de prueba de aceptación a partir de la especificación del requisito. | Q3: Propone SoPaMM, un metamodelo que vincula patrones de requisitos con patrones de prueba mediante conceptos de BDD, validado con un caso de autenticación web cuyas pruebas de aceptación se generan y ejecutan automáticamente.
A4: 3 | B4: Requisitos funcionales | C4: Ponencia de congreso | D4: 2024 | E4: 10.1145/3640310.3674093 | F4: A DSL for Testing LLMs for Fairness and Bias | G4: https://doi.org/10.1145/3640310.3674093 | H4: 1 | I4: 1 | J4: 0.5 | K4: 1 | L4: 3.5 | M4: - | N4: EthicalConcern, SensitiveCommunity, tolerance, delta, ReflectionType, InputType, Language (requisito ético); PromptTemplate, Oracle, TestScenario (artefactos de prueba) | O4: LangBiTe | P4: Un modelo de requisitos éticos definido con un DSL se transforma automáticamente en instancias de prompts (casos de prueba) que se ejecutan contra distintos LLMs y se evalúan mediante oráculos, dando trazabilidad extremo a extremo entre requisito y evaluación. | Q4: Propone LangBiTe, un enfoque dirigido por modelos con un DSL para especificar requisitos éticos (sesgo/discriminación) y generar, ejecutar y reportar automáticamente pruebas sobre LLMs, validado en un leaderboard con 16 modelos.
A5: 4 | B5: Requisitos funcionales | C5: Ponencia de congreso | D5: 2026 | E5: 10.5220/0014908300004030 | F5: A Framework for Integrated Behaviour Driven Development and Model Based Feature Design and Verification | G5: https://doi.org/10.5220/0014908300004030 | H5: 1 | I5: 1 | J5: 0.5 | K5: 1 | L5: 3.5 | M5: Gherkin/BDD, MBSE/SysML, EARS (mencionado en trabajo relacionado), ISO 26262 | N5: Escenarios Given-When-Then, feature files, requisitos identificados (RQ01-RQ05), state machines, señales enumeradas | O5: MagicDraw2024x (plugin MBT) + Behave (Python) + Simulink; caso Remote Keyless Entry (RKE) | P5: Los requisitos de experiencia de usuario se formalizan como escenarios Gherkin ejecutables que se corren automáticamente (Behave) contra modelos de comportamiento SysML (máquinas de estado) para verificar su cumplimiento upfront en el ciclo en V. | Q5: Propone un framework integrado BDD+MBSE que combina especificaciones Gherkin ejecutables y programación conductual para verificar tempranamente requisitos de features automotrices, demostrado con un caso de estudio de cierre remoto (RKE).
A6: 5 | B6: Requisitos funcionales | C6: Ponencia de congreso | D6: 2019 | E6: 10.1145/3297280.3297450 | F6: A Model-Driven Approach for Behavior-Driven GUI Testing | G6: https://doi.org/10.1145/3297280.3297450 | H6: 1 | I6: 1 | J6: 1 | K6: 1 | L6: 4 | M6: Gherkin/BDD, lenguaje ubicuo, Page Object pattern | N6: Feature, user story (As/I want/In order to), Scenario Given-When-Then, pantallas y widgets de wireframe, mapping de elementos | O6: Slang (integrado con Wireframesketcher) | P6: Las descripciones de features y escenarios estilo BDD se combinan con modelos de wireframe mediante un archivo de mapping para generar completamente scripts de prueba GUI ejecutables y page objects, eliminando la implementación manual de métodos de prueba. | Q6: Presenta Slang, un DSL que integra especificaciones BDD con modelos de wireframe de baja fidelidad para generar automáticamente casos de prueba de GUI, validado mediante un experimento controlado (63% menos tiempo que JBehave) y aplicación industrial en un banco.
A7: 6 | B7: Requisitos funcionales | C7: Ponencia de congreso | D7: 2023 | E7: 10.1109/re57278.2023.00013 | F7: A Requirements-Driven Platform for Validating Field Operations of Small Uncrewed Aerial Vehicles | G7: https://doi.org/10.1109/re57278.2023.00013 | H7: 1 | I7: 1 | J7: 1 | K7: 1 | L7: 4 | M7: - | N7: requisitos de sistema (RQ-0xx), propiedades de seguridad/test properties, monitores (C1.1, C1.2), configuración ambiental y de sUAS | O7: DroneReqValidator (DRV) | P7: Los requisitos de seguridad a nivel de sistema se traducen directamente en propiedades de prueba (test properties) y monitores configurables dentro de escenarios de prueba, que la plataforma ejecuta y evalúa automáticamente (incluyendo fuzzing) generando reportes PASSED/FAILED trazables al requisito. | Q7: Presenta DroneReqValidator (DRV), una plataforma dirigida por requisitos para simular y validar misiones de sUAS bajo condiciones ambientales realistas, evaluada en dos casos reales y un estudio de percepción con desarrolladores.
A8: 7 | B8: Requisitos funcionales | C8: Ponencia de congreso | D8: 2019 | E8: 10.1109/ret.2019.00009 | F8: A Software Tool to Convert Requirements to Test Cases | G8: https://doi.org/10.1109/ret.2019.00009 | H8: 1 | I8: 0.5 | J8: 0 | K8: 0.5 | L8: 2 | M8: Gherkin (Scenario Outline generado), User Stories | N8: Action Triad (Agent-Action-Concept), Dimension, Instance, escenario positivo/negativo, resultado esperado, ID de requisito | O8: TestAlgo | P8: Los requisitos de negocio se capturan como tríadas estructuradas (agente-acción-concepto con dimensiones e instancias) que un motor de optimización pairwise convierte automáticamente en historias de usuario, modelos de proceso y casos de prueba manuales con matriz de trazabilidad. | Q8: Presenta TestAlgo, una herramienta que implementa el método Action Triad para convertir requisitos de negocio estructurados en modelos (BPMN, casos de uso, historias de usuario) y artefactos de prueba (casos de prueba, RTM) generados automáticamente.
A9: 8 | B9: Requisitos funcionales | C9: Ponencia de congreso | D9: 2016 | E9: 10.1145/3011141.3011158 | F9: A Web Framework For Test Automation: User Scenarios Through User Interaction Diagrams | G9: https://doi.org/10.1145/3011141.3011158 | H9: 1 | I9: 1 | J9: 1 | K9: 1 | L9: 4 | M9: Acceptance Test-Driven Development (ATDD); US-UID/UID notation (no estándar formal ISO/IEEE) | N9: estados de interacción, entradas de usuario, salidas de sistema, transiciones, precondiciones (estado adicional de configuración), fixtures | O9: Framework web basado en FitNesse (editor de escenarios + User Scenario Runner + SLIM Executor) | P9: Los escenarios US-UID (representación de requisitos por el cliente) se convierten automáticamente en instrucciones SLIM/FitNesse ejecutables como pruebas de aceptación (ATDD). | Q9: Un framework web que ejecuta directamente diagramas US-UID como pruebas de aceptación automatizadas, evaluado con dos experimentos de mutación/eliminación de código sobre una aplicación web real.
A10: 9 | B10: Requisitos funcionales | C10: Ponencia de congreso | D10: 2018 | E10: 10.1109/icit.2018.00026 | F10: Achieving MC/DC using UML Communication Diagram | G10: https://doi.org/10.1109/icit.2018.00026 | H10: 1 | I10: 1 | J10: 0 | K10: 1 | L10: 3 | M10: DO-178B/DO-178C (criterio MC/DC); UML Communication Diagram (no estándar de requisitos textuales) | N10: objetos, actores, asociaciones, mensajes, condiciones de guarda | O10: MEUCD (MC/DC Estimator for UML Communication Diagram): Modelio + JiBX + jCUTE + COPECA | P10: El diagrama de comunicación UML (modelo de diseño derivado del caso de uso) se transforma en XSD y código Java, sobre el cual se generan automáticamente casos de prueba MC/DC mediante pruebas concólicas (jCUTE). | Q10: Una cadena de herramientas (MEUCD) que genera y mide automáticamente cobertura MC/DC a partir de diagramas de comunicación UML, validada en 15 casos de uso de 3 sistemas.
A11: 10 | B11: Requisitos funcionales | C11: Ponencia de congreso | D11: 2023 | E11: 10.1145/3613372.3613375 | F11: Adoption of the LGPD Inventory in the User Stories and BDD Scenarios Creation | G11: https://doi.org/10.1145/3613372.3613375 | H11: 1 | I11: 0.5 | J11: 1 | K11: 0.5 | L11: 3 | M11: LGPD (Brasil), GDPR (referencia), sintaxis de User Story (As/I can/So that), Gherkin/BDD (Given/When/Then) | N11: actores (titular de datos, agente de tratamiento, encargado), funcionalidad/proceso de tratamiento, precondiciones (hipótesis legal), finalidad de la funcionalidad | O11: - | P11: Propone un mapeo entre los elementos del Inventario de Datos Personales (IDP/LGPD) y las cláusulas de User Stories y escenarios BDD, que alimentan indirectamente la generación de pruebas de aceptación basadas en BDD. | Q11: Un mapeo documental entre elementos obligatorios del Inventario de Datos Personales (LGPD) y las cláusulas de User Stories/Escenarios BDD para apoyar la especificación ágil de requisitos de privacidad.
A12: 11 | B12: Requisitos funcionales | C12: Articulo de revista | D12: 2026 | E12: 10.1109/ojcoms.2026.3686199 | F12: Agentic-AI Framework for Integrated Design, Implementation, Testing, and Operation of Digital Twin Networks | G12: https://doi.org/10.1109/ojcoms.2026.3686199 | H12: 1 | I12: 1 | J12: 1 | K12: 1 | L12: 4 | M12: - | N12: descripción de caso de uso (use-case formalizado), KPIs cuantificados (requisitos medibles), contexto de descubrimiento de red, diseño/plan de aplicaciones, suite de pruebas | O12: Framework agéntico multi-LLM (Orquestador LangGraph/FastAPI con agentes de Percepción, Reflexión, Planificador, Generador de Código, Sandbox de validación y Control) | P12: Los requisitos se capturan como descripciones de caso de uso formalizadas y KPIs cuantificados, que impulsan un ciclo iterativo de TDD automatizado por LLM (generación de código y suite de pruebas, validación en sandbox antes de actuar sobre la red física). | Q12: Un framework agéntico de extremo a extremo que automatiza la especificación de requisitos (KPIs), diseño, generación de código y pruebas (ciclo TDD asistido por LLM), y operación de Redes Gemelas Digitales, evaluado con múltiples LLMs en dos casos de uso 6G.
A13: 12 | B13: Requisitos funcionales | C13: Articulo de revista | D13: 2023 | E13: 10.1007/s00766-022-00377-5 | F13: Aligning requirements and testing through metamodeling and patterns: design and evaluation | G13: https://doi.org/10.1007/s00766-022-00377-5 | H13: 1 | I13: 1 | J13: 1 | K13: 1 | L13: 4 | M13: Sintaxis de User Story, Gherkin/BDD, ISO/IEC 25010, ISO/IEC 9126, MOF | N13: Feature (As/I_can/So_that), Scenario (Given/When/Then), Example (datos de prueba), caso de prueba (precondiciones, resultados esperados, poscondiciones) | O13: Metamodelo SoPaMM (Software Pattern MetaModel) + herramienta TMEd (Terminal Model Editor) | P13: Los Patrones de Requisito Funcional (user story + escenarios Gherkin) se vinculan formalmente mediante el metamodelo SoPaMM con Patrones de Prueba de Aceptación, permitiendo derivar casos de prueba trazables a partir de los requisitos. | Q13: Un metamodelo (SoPaMM) que alinea patrones de requisitos funcionales y patrones de prueba de aceptación mediante notación BDD, evaluado en calidad con el framework MQuaRE por 6 evaluadores expertos.
... A109: 108 | B109: Historias de usuario | C109: Articulo de revista | D109: 2016 | E109: 10.1007/978-3-319-30282-9 | F109: The Use and Effectiveness of User Stories in Practice | G109: https://doi.org/10.1007/978-3-319-30282-9 | H109: 1 | I109: 1 | J109: 1 | K109: 1 | L109: 4 | M109: Plantilla Connextra; guía de calidad INVEST | N109: rol (type of user), objetivo (goal), beneficio (so that) | O109: - | P109: No genera pruebas directamente, pero aporta evidencia empírica sobre plantillas y guías de calidad (INVEST) que sustentan la estructuración de HU previa a cualquier derivación posterior de pruebas. | Q109: Encuesta con 182 respuestas válidas y 21 entrevistas de seguimiento que analiza el uso de plantillas de HU y guías de calidad (INVEST) y su percepción de efectividad en productividad y calidad de los entregables, con amenazas a la validez discutidas explícitamente.

Sheet Estudios excluidos
A1: N° | B1: Categoría | C1: Tipo | D1: Año | E1: DOI | F1: Título | G1: Enlace | H1: Calidad (0-4) | I1: Motivo de exclusión | J1: Detalle
A2: 1 | B2: Requisitos funcionales | C2: Articulo de revista | D2: 2016 | E2: 10.1145/3036686.3036691 | F2: A Model Based Design Approach To System Building Using The e-Yantra Educational Robot | G2: https://doi.org/10.1145/3036686.3036691 | H2: 3 | I2: Fuera de alcance temático | J2: Baja relevancia: se centra en diseño basado en modelos (UML state machines) y aprendizaje por proyectos en robótica educativa, sin abordar captura estructurada de requisitos funcionales/historias de usuario orientada a la generación automática de pruebas.
A3: 2 | B3: Requisitos funcionales | C3: Ponencia de congreso | D3: 2018 | E3: 10.1145/3197091.3197096 | F3: A Safety-Aware, Systems-Based Approach to Teaching Software Testing | G3: https://doi.org/10.1145/3197091.3197096 | H3: 3.5 | I3: Fuera de alcance temático | J3: Baja relevancia: artículo pedagógico sobre enseñanza de pruebas de software; no trata captura estructurada de requisitos ni generación automática de pruebas a partir de ellos (TDD/TDDMachine).
A4: 3 | B4: Requisitos funcionales | C4: Ponencia de congreso | D4: 2022 | E4: 10.1109/qrs57517.2022.00027 | F4: An Empirical Study on Software Defect Prediction using Function Point Analysis | G4: https://doi.org/10.1109/qrs57517.2022.00027 | H4: 4 | I4: Fuera de alcance temático | J4: Fuera de alcance temático: aborda predicción de defectos a partir de tamaño de requisitos (function points), no captura estructurada de requisitos ni generación/derivación de pruebas.
A5: 4 | B5: Requisitos funcionales | C5: Ponencia de congreso | D5: 2022 | E5: 10.1145/3551349.3563241 | F5: Application of Natural Language Processing Towards Autonomous Software Testing | G5: https://doi.org/10.1145/3551349.3563241 | H5: 2 | I5: Estudio secundario | J5: Es un artículo de panorama/overview sin metodología sistemática ni contribución primaria propia (no reporta experimento u ontología/herramienta propia con evaluación original).
A6: 5 | B6: Requisitos funcionales | C6: Ponencia de congreso | D6: 2021 | E6: 10.1109/icit52682.2021.9491761 | F6: Automated Test Cases Generation From Requirements Specification | G6: https://doi.org/10.1109/icit52682.2021.9491761 | H6: 1.5 | I6: Calidad insuficiente | J6: Carece de validación empírica y de discusión de limitaciones o amenazas a la validez; el enfoque solo se describe conceptualmente mediante algoritmos, sin experimentos ni resultados.
A7: 6 | B7: Requisitos funcionales | C7: Ponencia de congreso | D7: 2019 | E7: 10.1109/apsec.2018.00086 | F7: Automated code-based test selection for software product line regression testing | G7: https://doi.org/10.1109/apsec.2018.00086 | H7: 4 | I7: Fuera de alcance temático | J7: Fuera de alcance temático: no aborda captura de requisitos ni generación/derivación de pruebas a partir de especificaciones; es selección de pruebas de regresión basada exclusivamente en código fuente.
A8: 7 | B8: Requisitos funcionales | C8: Ponencia de congreso | D8: 2020 | E8: 10.1145/3422392.3422460 | F8: Behavior-Driven Development: An Expert Panel to evaluate benefits and challenges | G8: https://doi.org/10.1145/3422392.3422460 | H8: 4 | I8: Fuera de alcance temático | J8: Estudio cualitativo de percepciones sobre enseñanza de BDD; no presenta método técnico ni herramienta de captura estructurada de requisitos ni de generación/derivación de pruebas.
A9: 8 | B9: Requisitos funcionales | C9: Ponencia de congreso | D9: 2019 | E9: 10.1007/978-3-030-21348-0_29 | F9: CORAL: A Corpus of Ontological Requirements Annotated with Lexico-Syntactic Patterns | G9: https://doi.org/10.1007/978-3-030-21348-0_29 | H9: 3.5 | I9: Fuera de alcance temático | J9: Dominio de ingeniería de ontologías (competency questions), no aborda requisitos funcionales/casos de uso/historias de usuario de software ni su vínculo con generación de pruebas TDD.
A10: 9 | B10: Requisitos funcionales | C10: Ponencia de congreso | D10: 2020 | E10: 10.1109/aitest49225.2020.00022 | F10: Cluster-Based Parallel Testing Using Semantic Analysis | G10: https://doi.org/10.1109/aitest49225.2020.00022 | H10: 4 | I10: Fuera de alcance temático | J10: No aborda la captura estructurada de requisitos ni la generación/derivación de pruebas a partir de ellos; se centra en optimización y agrupamiento de test cases ya redactados.
A11: 10 | B11: Requisitos funcionales | C11: Ponencia de congreso | D11: 2016 | E11: 10.1109/re.2016.12 | F11: Definition of a Behavior-Driven Model for Requirements Specification and Testing of Interactive Systems | G11: https://doi.org/10.1109/re.2016.12 | H11: 1.5 | I11: Calidad insuficiente | J11: Artículo de simposio doctoral (propuesta de tesis) sin resultados empíricos ejecutados: la validación se presenta solo como plan futuro, sin discusión de amenazas a la validez ni evidencia de resultados.
A12: 11 | B12: Requisitos funcionales | C12: Articulo de revista | D12: 2018 | E12: 10.1145/3176643 | F12: Detecting the Behavior of Design Patterns through Model Checking and Dynamic Analysis | G12: https://doi.org/10.1145/3176643 | H12: 4 | I12: Fuera de alcance temático | J12: No aborda captura estructurada de requisitos (requisitos funcionales, casos de uso, historias de usuario) ni la generación de pruebas a partir de ellos; es un trabajo de ingeniería inversa de patrones de diseño en código, ajeno al alcance de la SLR.
A13: 12 | B13: Requisitos funcionales | C13: Ponencia de congreso | D13: 2018 | E13: 10.1145/3167132.3167344 | F13: EffTE: A Dependency-aware Approach for Test-Driven Ontology Development | G13: https://doi.org/10.1145/3167132.3167344 | H13: 3.5 | I13: Fuera de alcance temático | J13: El foco es la eficiencia de re-evaluación de pruebas de ontologías mediante un grafo de dependencias, no la captura estructurada de requisitos funcionales/historias de usuario ni su vínculo con la generación automática de pruebas de software bajo TDD.
... A47: 46 | B47: Historias de usuario | C47: Ponencia de congreso | D47: 2019 | E47: — | F47: Test Suite Reduction based on knowledge Reuse: An Adaptive Elitism Based Intellect approach (AEBI) using Clustering Technique | G47: https://scholar.google.com/scholar?q=Test%20Suite%20Reduction%20based%20on%20knowledge%20Reuse%3A%20An%20Adaptive%20Elitism%20Based%20Intellect%20approach%20%28AEBI%29%20using%20Clustering%20Technique | H47: 2 | I47: Fuera de alcance temático | J47: Baja relevancia: el contenido real del artículo (a pesar del nombre de archivo) no aborda historias de usuario, casos de uso ni captura estructurada de requisitos; es una técnica de optimización/reducción de test suites mediante metaheurística, ajena al foco de la revisión.
